[
  {
    "trial_number": 0,
    "params": {
      "min_data_in_leaf": 112,
      "num_leaves": 24,
      "learning_rate": 0.008265525431611562,
      "feature_fraction": 0.17351952362504955,
      "bagging_fraction": 0.6597690185429134
    },
    "value": 2239300000.0,
    "datetime": "2025-10-23T19:52:37.701388",
    "state": "COMPLETE",
    "configuracion": {
      "semilla": 80021,
      "mes_train": [
        202101,
        202102,
        202103
      ],
      "mes_validacion": 202104
    }
  },
  {
    "trial_number": 1,
    "params": {
      "min_data_in_leaf": 243,
      "num_leaves": 24,
      "learning_rate": 0.011466177377970625,
      "feature_fraction": 0.8341021152316814,
      "bagging_fraction": 0.6862284314278664
    },
    "value": 2343260000.0,
    "datetime": "2025-10-23T19:53:08.947825",
    "state": "COMPLETE",
    "configuracion": {
      "semilla": 80021,
      "mes_train": [
        202101,
        202102,
        202103
      ],
      "mes_validacion": 202104
    }
  },
  {
    "trial_number": 2,
    "params": {
      "min_data_in_leaf": 72,
      "num_leaves": 49,
      "learning_rate": 0.07563688108438833,
      "feature_fraction": 0.44618746727688374,
      "bagging_fraction": 0.5234255420571207
    },
    "value": 2519920000.0,
    "datetime": "2025-10-23T19:53:55.006038",
    "state": "COMPLETE",
    "configuracion": {
      "semilla": 80021,
      "mes_train": [
        202101,
        202102,
        202103
      ],
      "mes_validacion": 202104
    }
  },
  {
    "trial_number": 3,
    "params": {
      "min_data_in_leaf": 34,
      "num_leaves": 32,
      "learning_rate": 0.09718233543327506,
      "feature_fraction": 0.46128359168998545,
      "bagging_fraction": 0.28319013064366205
    },
    "value": 2454840000.0,
    "datetime": "2025-10-23T19:54:39.076819",
    "state": "COMPLETE",
    "configuracion": {
      "semilla": 80021,
      "mes_train": [
        202101,
        202102,
        202103
      ],
      "mes_validacion": 202104
    }
  },
  {
    "trial_number": 4,
    "params": {
      "min_data_in_leaf": 794,
      "num_leaves": 62,
      "learning_rate": 0.08190741440202726,
      "feature_fraction": 0.3622015988952788,
      "bagging_fraction": 0.7355707551853378
    },
    "value": 2558780000.0,
    "datetime": "2025-10-23T19:55:27.010475",
    "state": "COMPLETE",
    "configuracion": {
      "semilla": 80021,
      "mes_train": [
        202101,
        202102,
        202103
      ],
      "mes_validacion": 202104
    }
  },
  {
    "trial_number": 0,
    "params": {
      "min_data_in_leaf": 112,
      "num_leaves": 24,
      "learning_rate": 0.008265525431611562,
      "feature_fraction": 0.17351952362504955,
      "bagging_fraction": 0.6597690185429134
    },
    "value": 2239320000.0,
    "datetime": "2025-10-23T19:58:30.967481",
    "state": "COMPLETE",
    "configuracion": {
      "semilla": 80021,
      "mes_train": [
        202101,
        202102,
        202103
      ],
      "mes_validacion": 202104
    }
  },
  {
    "trial_number": 1,
    "params": {
      "min_data_in_leaf": 243,
      "num_leaves": 24,
      "learning_rate": 0.011466177377970625,
      "feature_fraction": 0.8341021152316814,
      "bagging_fraction": 0.6862284314278664
    },
    "value": 2351380000.0,
    "datetime": "2025-10-23T19:58:55.789895",
    "state": "COMPLETE",
    "configuracion": {
      "semilla": 80021,
      "mes_train": [
        202101,
        202102,
        202103
      ],
      "mes_validacion": 202104
    }
  },
  {
    "trial_number": 2,
    "params": {
      "min_data_in_leaf": 72,
      "num_leaves": 49,
      "learning_rate": 0.07563688108438833,
      "feature_fraction": 0.44618746727688374,
      "bagging_fraction": 0.5234255420571207
    },
    "value": 2527200000.0,
    "datetime": "2025-10-23T19:59:36.486112",
    "state": "COMPLETE",
    "configuracion": {
      "semilla": 80021,
      "mes_train": [
        202101,
        202102,
        202103
      ],
      "mes_validacion": 202104
    }
  },
  {
    "trial_number": 3,
    "params": {
      "min_data_in_leaf": 34,
      "num_leaves": 32,
      "learning_rate": 0.09718233543327506,
      "feature_fraction": 0.46128359168998545,
      "bagging_fraction": 0.28319013064366205
    },
    "value": 2458760000.0,
    "datetime": "2025-10-23T20:00:15.450822",
    "state": "COMPLETE",
    "configuracion": {
      "semilla": 80021,
      "mes_train": [
        202101,
        202102,
        202103
      ],
      "mes_validacion": 202104
    }
  },
  {
    "trial_number": 4,
    "params": {
      "min_data_in_leaf": 794,
      "num_leaves": 62,
      "learning_rate": 0.08190741440202726,
      "feature_fraction": 0.3622015988952788,
      "bagging_fraction": 0.7355707551853378
    },
    "value": 2551760000.0,
    "datetime": "2025-10-23T20:00:57.184218",
    "state": "COMPLETE",
    "configuracion": {
      "semilla": 80021,
      "mes_train": [
        202101,
        202102,
        202103
      ],
      "mes_validacion": 202104
    }
  },
  {
    "trial_number": 0,
    "params": {
      "min_data_in_leaf": 112,
      "num_leaves": 24,
      "learning_rate": 0.008265525431611562,
      "feature_fraction": 0.17351952362504955,
      "bagging_fraction": 0.6597690185429134
    },
    "value": 2234000000.0,
    "datetime": "2025-10-24T17:13:33.842208",
    "state": "COMPLETE",
    "configuracion": {
      "semilla": 80021,
      "mes_train": [
        202101,
        202102,
        202103
      ],
      "mes_validacion": 202104
    }
  },
  {
    "trial_number": 1,
    "params": {
      "min_data_in_leaf": 243,
      "num_leaves": 24,
      "learning_rate": 0.011466177377970625,
      "feature_fraction": 0.8341021152316814,
      "bagging_fraction": 0.6862284314278664
    },
    "value": 2339400000.0,
    "datetime": "2025-10-24T17:13:57.188417",
    "state": "COMPLETE",
    "configuracion": {
      "semilla": 80021,
      "mes_train": [
        202101,
        202102,
        202103
      ],
      "mes_validacion": 202104
    }
  },
  {
    "trial_number": 2,
    "params": {
      "min_data_in_leaf": 72,
      "num_leaves": 49,
      "learning_rate": 0.07563688108438833,
      "feature_fraction": 0.44618746727688374,
      "bagging_fraction": 0.5234255420571207
    },
    "value": 2511220000.0,
    "datetime": "2025-10-24T17:14:35.530899",
    "state": "COMPLETE",
    "configuracion": {
      "semilla": 80021,
      "mes_train": [
        202101,
        202102,
        202103
      ],
      "mes_validacion": 202104
    }
  },
  {
    "trial_number": 3,
    "params": {
      "min_data_in_leaf": 34,
      "num_leaves": 32,
      "learning_rate": 0.09718233543327506,
      "feature_fraction": 0.46128359168998545,
      "bagging_fraction": 0.28319013064366205
    },
    "value": 2459640000.0,
    "datetime": "2025-10-24T17:15:12.614097",
    "state": "COMPLETE",
    "configuracion": {
      "semilla": 80021,
      "mes_train": [
        202101,
        202102,
        202103
      ],
      "mes_validacion": 202104
    }
  },
  {
    "trial_number": 4,
    "params": {
      "min_data_in_leaf": 794,
      "num_leaves": 62,
      "learning_rate": 0.08190741440202726,
      "feature_fraction": 0.3622015988952788,
      "bagging_fraction": 0.7355707551853378
    },
    "value": 2572120000.0,
    "datetime": "2025-10-24T17:15:52.330902",
    "state": "COMPLETE",
    "configuracion": {
      "semilla": 80021,
      "mes_train": [
        202101,
        202102,
        202103
      ],
      "mes_validacion": 202104
    }
  }
]